<experiments>
	<experiment name="nc8-cpv1-idf1-psBAL_ONE-ppFalse" trials="1">
		<clusters>
			<cluster>
				<app name="npb-mg" runs="2">
				    <args>8 C</args>
					<tuning>
						<procpin>False</procpin>
					</tuning>
				</app>
				<topology nc="8" cpv="1" />
				<mapping idf="1" pstrat="BAL_ONE" />
			</cluster>
		</clusters>
	</experiment>
	<experiment name="nc8-cpv1-idf1-psNONE-ppFalse" trials="1">
		<clusters>
			<cluster>
				<app name="npb-mg" runs="2">
				    <args>8 C</args>
					<tuning>
						<procpin>False</procpin>
					</tuning>
				</app>
				<topology nc="8" cpv="1" />
				<mapping idf="1" pstrat="NONE" />
			</cluster>
		</clusters>
	</experiment>
	<experiment name="nc16-cpv1-idf2-psBAL_ONE-ppFalse" trials="1">
		<clusters>
			<cluster>
				<app name="npb-mg" runs="2">
				    <args>16 C</args>
					<tuning>
						<procpin>False</procpin>
					</tuning>
				</app>
				<topology nc="16" cpv="1" />
				<mapping idf="2" pstrat="BAL_ONE" />
			</cluster>
		</clusters>
	</experiment>
	<experiment name="nc16-cpv1-idf2-psNONE-ppFalse" trials="1">
		<clusters>
			<cluster>
				<app name="npb-mg" runs="2">
				    <args>16 C</args>
					<tuning>
						<procpin>False</procpin>
					</tuning>
				</app>
				<topology nc="16" cpv="1" />
				<mapping idf="2" pstrat="NONE" />
			</cluster>
		</clusters>
	</experiment>
	<experiment name="nc8-cpv1-idf2-psBAL_ONE-ppFalse" trials="1">
		<clusters>
			<cluster>
				<app name="npb-mg" runs="2">
				    <args>8 C</args>
					<tuning>
						<procpin>False</procpin>
					</tuning>
				</app>
				<topology nc="8" cpv="1" />
				<mapping idf="2" pstrat="BAL_ONE" />
			</cluster>
		</clusters>
	</experiment>
	<experiment name="nc8-cpv1-idf2-psNONE-ppFalse" trials="1">
		<clusters>
			<cluster>
				<app name="npb-mg" runs="2">
				    <args>8 C</args>
					<tuning>
						<procpin>False</procpin>
					</tuning>
				</app>
				<topology nc="8" cpv="1" />
				<mapping idf="2" pstrat="NONE" />
			</cluster>
		</clusters>
	</experiment>
	<experiment name="nc32-cpv1-idf4-psBAL_ONE-ppFalse" trials="1">
		<clusters>
			<cluster>
				<app name="npb-mg" runs="2">
				    <args>32 C</args>
					<tuning>
						<procpin>False</procpin>
					</tuning>
				</app>
				<topology nc="32" cpv="1" />
				<mapping idf="4" pstrat="BAL_ONE" />
			</cluster>
		</clusters>
	</experiment>
	<experiment name="nc32-cpv1-idf4-psNONE-ppFalse" trials="1">
		<clusters>
			<cluster>
				<app name="npb-mg" runs="2">
				    <args>32 C</args>
					<tuning>
						<procpin>False</procpin>
					</tuning>
				</app>
				<topology nc="32" cpv="1" />
				<mapping idf="4" pstrat="NONE" />
			</cluster>
		</clusters>
	</experiment>
	<experiment name="nc16-cpv1-idf4-psBAL_ONE-ppFalse" trials="1">
		<clusters>
			<cluster>
				<app name="npb-mg" runs="2">
				    <args>16 C</args>
					<tuning>
						<procpin>False</procpin>
					</tuning>
				</app>
				<topology nc="16" cpv="1" />
				<mapping idf="4" pstrat="BAL_ONE" />
			</cluster>
		</clusters>
	</experiment>
	<experiment name="nc16-cpv1-idf4-psNONE-ppFalse" trials="1">
		<clusters>
			<cluster>
				<app name="npb-mg" runs="2">
				    <args>16 C</args>
					<tuning>
						<procpin>False</procpin>
					</tuning>
				</app>
				<topology nc="16" cpv="1" />
				<mapping idf="4" pstrat="NONE" />
			</cluster>
		</clusters>
	</experiment>
	<experiment name="nc8-cpv1-idf4-psBAL_ONE-ppFalse" trials="1">
		<clusters>
			<cluster>
				<app name="npb-mg" runs="2">
				    <args>8 C</args>
					<tuning>
						<procpin>False</procpin>
					</tuning>
				</app>
				<topology nc="8" cpv="1" />
				<mapping idf="4" pstrat="BAL_ONE" />
			</cluster>
		</clusters>
	</experiment>
	<experiment name="nc8-cpv1-idf4-psNONE-ppFalse" trials="1">
		<clusters>
			<cluster>
				<app name="npb-mg" runs="2">
				    <args>8 C</args>
					<tuning>
						<procpin>False</procpin>
					</tuning>
				</app>
				<topology nc="8" cpv="1" />
				<mapping idf="4" pstrat="NONE" />
			</cluster>
		</clusters>
	</experiment>
	<experiment name="nc64-cpv1-idf8-psBAL_ONE-ppFalse" trials="1">
		<clusters>
			<cluster>
				<app name="npb-mg" runs="2">
				    <args>64 C</args>
					<tuning>
						<procpin>False</procpin>
					</tuning>
				</app>
				<topology nc="64" cpv="1" />
				<mapping idf="8" pstrat="BAL_ONE" />
			</cluster>
		</clusters>
	</experiment>
	<experiment name="nc64-cpv1-idf8-psNONE-ppFalse" trials="1">
		<clusters>
			<cluster>
				<app name="npb-mg" runs="2">
				    <args>64 C</args>
					<tuning>
						<procpin>False</procpin>
					</tuning>
				</app>
				<topology nc="64" cpv="1" />
				<mapping idf="8" pstrat="NONE" />
			</cluster>
		</clusters>
	</experiment>
	<experiment name="nc32-cpv1-idf8-psBAL_ONE-ppFalse" trials="1">
		<clusters>
			<cluster>
				<app name="npb-mg" runs="2">
				    <args>32 C</args>
					<tuning>
						<procpin>False</procpin>
					</tuning>
				</app>
				<topology nc="32" cpv="1" />
				<mapping idf="8" pstrat="BAL_ONE" />
			</cluster>
		</clusters>
	</experiment>
	<experiment name="nc32-cpv1-idf8-psNONE-ppFalse" trials="1">
		<clusters>
			<cluster>
				<app name="npb-mg" runs="2">
				    <args>32 C</args>
					<tuning>
						<procpin>False</procpin>
					</tuning>
				</app>
				<topology nc="32" cpv="1" />
				<mapping idf="8" pstrat="NONE" />
			</cluster>
		</clusters>
	</experiment>
	<experiment name="nc16-cpv1-idf8-psBAL_ONE-ppFalse" trials="1">
		<clusters>
			<cluster>
				<app name="npb-mg" runs="2">
				    <args>16 C</args>
					<tuning>
						<procpin>False</procpin>
					</tuning>
				</app>
				<topology nc="16" cpv="1" />
				<mapping idf="8" pstrat="BAL_ONE" />
			</cluster>
		</clusters>
	</experiment>
	<experiment name="nc16-cpv1-idf8-psNONE-ppFalse" trials="1">
		<clusters>
			<cluster>
				<app name="npb-mg" runs="2">
				    <args>16 C</args>
					<tuning>
						<procpin>False</procpin>
					</tuning>
				</app>
				<topology nc="16" cpv="1" />
				<mapping idf="8" pstrat="NONE" />
			</cluster>
		</clusters>
	</experiment>
	<experiment name="nc8-cpv1-idf8-psBAL_ONE-ppFalse" trials="1">
		<clusters>
			<cluster>
				<app name="npb-mg" runs="2">
				    <args>8 C</args>
					<tuning>
						<procpin>False</procpin>
					</tuning>
				</app>
				<topology nc="8" cpv="1" />
				<mapping idf="8" pstrat="BAL_ONE" />
			</cluster>
		</clusters>
	</experiment>
	<experiment name="nc8-cpv1-idf8-psNONE-ppFalse" trials="1">
		<clusters>
			<cluster>
				<app name="npb-mg" runs="2">
				    <args>8 C</args>
					<tuning>
						<procpin>False</procpin>
					</tuning>
				</app>
				<topology nc="8" cpv="1" />
				<mapping idf="8" pstrat="NONE" />
			</cluster>
		</clusters>
	</experiment>
	<experiment name="nc16-cpv2-idf2-psBAL_ONE-ppFalse" trials="1">
		<clusters>
			<cluster>
				<app name="npb-mg" runs="2">
				    <args>16 C</args>
					<tuning>
						<procpin>False</procpin>
					</tuning>
				</app>
				<topology nc="16" cpv="2" />
				<mapping idf="2" pstrat="BAL_ONE" />
			</cluster>
		</clusters>
	</experiment>
	<experiment name="nc16-cpv2-idf2-psNONE-ppFalse" trials="1">
		<clusters>
			<cluster>
				<app name="npb-mg" runs="2">
				    <args>16 C</args>
					<tuning>
						<procpin>False</procpin>
					</tuning>
				</app>
				<topology nc="16" cpv="2" />
				<mapping idf="2" pstrat="NONE" />
			</cluster>
		</clusters>
	</experiment>
	<experiment name="nc8-cpv2-idf2-psBAL_ONE-ppFalse" trials="1">
		<clusters>
			<cluster>
				<app name="npb-mg" runs="2">
				    <args>8 C</args>
					<tuning>
						<procpin>False</procpin>
					</tuning>
				</app>
				<topology nc="8" cpv="2" />
				<mapping idf="2" pstrat="BAL_ONE" />
			</cluster>
		</clusters>
	</experiment>
	<experiment name="nc8-cpv2-idf2-psNONE-ppFalse" trials="1">
		<clusters>
			<cluster>
				<app name="npb-mg" runs="2">
				    <args>8 C</args>
					<tuning>
						<procpin>False</procpin>
					</tuning>
				</app>
				<topology nc="8" cpv="2" />
				<mapping idf="2" pstrat="NONE" />
			</cluster>
		</clusters>
	</experiment>
	<experiment name="nc32-cpv2-idf4-psBAL_ONE-ppFalse" trials="1">
		<clusters>
			<cluster>
				<app name="npb-mg" runs="2">
				    <args>32 C</args>
					<tuning>
						<procpin>False</procpin>
					</tuning>
				</app>
				<topology nc="32" cpv="2" />
				<mapping idf="4" pstrat="BAL_ONE" />
			</cluster>
		</clusters>
	</experiment>
	<experiment name="nc32-cpv2-idf4-psNONE-ppFalse" trials="1">
		<clusters>
			<cluster>
				<app name="npb-mg" runs="2">
				    <args>32 C</args>
					<tuning>
						<procpin>False</procpin>
					</tuning>
				</app>
				<topology nc="32" cpv="2" />
				<mapping idf="4" pstrat="NONE" />
			</cluster>
		</clusters>
	</experiment>
	<experiment name="nc16-cpv2-idf4-psBAL_ONE-ppFalse" trials="1">
		<clusters>
			<cluster>
				<app name="npb-mg" runs="2">
				    <args>16 C</args>
					<tuning>
						<procpin>False</procpin>
					</tuning>
				</app>
				<topology nc="16" cpv="2" />
				<mapping idf="4" pstrat="BAL_ONE" />
			</cluster>
		</clusters>
	</experiment>
	<experiment name="nc16-cpv2-idf4-psNONE-ppFalse" trials="1">
		<clusters>
			<cluster>
				<app name="npb-mg" runs="2">
				    <args>16 C</args>
					<tuning>
						<procpin>False</procpin>
					</tuning>
				</app>
				<topology nc="16" cpv="2" />
				<mapping idf="4" pstrat="NONE" />
			</cluster>
		</clusters>
	</experiment>
	<experiment name="nc8-cpv2-idf4-psBAL_ONE-ppFalse" trials="1">
		<clusters>
			<cluster>
				<app name="npb-mg" runs="2">
				    <args>8 C</args>
					<tuning>
						<procpin>False</procpin>
					</tuning>
				</app>
				<topology nc="8" cpv="2" />
				<mapping idf="4" pstrat="BAL_ONE" />
			</cluster>
		</clusters>
	</experiment>
	<experiment name="nc8-cpv2-idf4-psNONE-ppFalse" trials="1">
		<clusters>
			<cluster>
				<app name="npb-mg" runs="2">
				    <args>8 C</args>
					<tuning>
						<procpin>False</procpin>
					</tuning>
				</app>
				<topology nc="8" cpv="2" />
				<mapping idf="4" pstrat="NONE" />
			</cluster>
		</clusters>
	</experiment>
	<experiment name="nc64-cpv2-idf8-psBAL_ONE-ppFalse" trials="1">
		<clusters>
			<cluster>
				<app name="npb-mg" runs="2">
				    <args>64 C</args>
					<tuning>
						<procpin>False</procpin>
					</tuning>
				</app>
				<topology nc="64" cpv="2" />
				<mapping idf="8" pstrat="BAL_ONE" />
			</cluster>
		</clusters>
	</experiment>
	<experiment name="nc64-cpv2-idf8-psNONE-ppFalse" trials="1">
		<clusters>
			<cluster>
				<app name="npb-mg" runs="2">
				    <args>64 C</args>
					<tuning>
						<procpin>False</procpin>
					</tuning>
				</app>
				<topology nc="64" cpv="2" />
				<mapping idf="8" pstrat="NONE" />
			</cluster>
		</clusters>
	</experiment>
	<experiment name="nc32-cpv2-idf8-psBAL_ONE-ppFalse" trials="1">
		<clusters>
			<cluster>
				<app name="npb-mg" runs="2">
				    <args>32 C</args>
					<tuning>
						<procpin>False</procpin>
					</tuning>
				</app>
				<topology nc="32" cpv="2" />
				<mapping idf="8" pstrat="BAL_ONE" />
			</cluster>
		</clusters>
	</experiment>
	<experiment name="nc32-cpv2-idf8-psNONE-ppFalse" trials="1">
		<clusters>
			<cluster>
				<app name="npb-mg" runs="2">
				    <args>32 C</args>
					<tuning>
						<procpin>False</procpin>
					</tuning>
				</app>
				<topology nc="32" cpv="2" />
				<mapping idf="8" pstrat="NONE" />
			</cluster>
		</clusters>
	</experiment>
	<experiment name="nc16-cpv2-idf8-psBAL_ONE-ppFalse" trials="1">
		<clusters>
			<cluster>
				<app name="npb-mg" runs="2">
				    <args>16 C</args>
					<tuning>
						<procpin>False</procpin>
					</tuning>
				</app>
				<topology nc="16" cpv="2" />
				<mapping idf="8" pstrat="BAL_ONE" />
			</cluster>
		</clusters>
	</experiment>
	<experiment name="nc16-cpv2-idf8-psNONE-ppFalse" trials="1">
		<clusters>
			<cluster>
				<app name="npb-mg" runs="2">
				    <args>16 C</args>
					<tuning>
						<procpin>False</procpin>
					</tuning>
				</app>
				<topology nc="16" cpv="2" />
				<mapping idf="8" pstrat="NONE" />
			</cluster>
		</clusters>
	</experiment>
	<experiment name="nc8-cpv2-idf8-psBAL_ONE-ppFalse" trials="1">
		<clusters>
			<cluster>
				<app name="npb-mg" runs="2">
				    <args>8 C</args>
					<tuning>
						<procpin>False</procpin>
					</tuning>
				</app>
				<topology nc="8" cpv="2" />
				<mapping idf="8" pstrat="BAL_ONE" />
			</cluster>
		</clusters>
	</experiment>
	<experiment name="nc8-cpv2-idf8-psNONE-ppFalse" trials="1">
		<clusters>
			<cluster>
				<app name="npb-mg" runs="2">
				    <args>8 C</args>
					<tuning>
						<procpin>False</procpin>
					</tuning>
				</app>
				<topology nc="8" cpv="2" />
				<mapping idf="8" pstrat="NONE" />
			</cluster>
		</clusters>
	</experiment>
	<experiment name="nc32-cpv4-idf4-psBAL_ONE-ppFalse" trials="1">
		<clusters>
			<cluster>
				<app name="npb-mg" runs="2">
				    <args>32 C</args>
					<tuning>
						<procpin>False</procpin>
					</tuning>
				</app>
				<topology nc="32" cpv="4" />
				<mapping idf="4" pstrat="BAL_ONE" />
			</cluster>
		</clusters>
	</experiment>
	<experiment name="nc32-cpv4-idf4-psNONE-ppFalse" trials="1">
		<clusters>
			<cluster>
				<app name="npb-mg" runs="2">
				    <args>32 C</args>
					<tuning>
						<procpin>False</procpin>
					</tuning>
				</app>
				<topology nc="32" cpv="4" />
				<mapping idf="4" pstrat="NONE" />
			</cluster>
		</clusters>
	</experiment>
	<experiment name="nc16-cpv4-idf4-psBAL_ONE-ppFalse" trials="1">
		<clusters>
			<cluster>
				<app name="npb-mg" runs="2">
				    <args>16 C</args>
					<tuning>
						<procpin>False</procpin>
					</tuning>
				</app>
				<topology nc="16" cpv="4" />
				<mapping idf="4" pstrat="BAL_ONE" />
			</cluster>
		</clusters>
	</experiment>
	<experiment name="nc16-cpv4-idf4-psNONE-ppFalse" trials="1">
		<clusters>
			<cluster>
				<app name="npb-mg" runs="2">
				    <args>16 C</args>
					<tuning>
						<procpin>False</procpin>
					</tuning>
				</app>
				<topology nc="16" cpv="4" />
				<mapping idf="4" pstrat="NONE" />
			</cluster>
		</clusters>
	</experiment>
	<experiment name="nc8-cpv4-idf4-psBAL_ONE-ppFalse" trials="1">
		<clusters>
			<cluster>
				<app name="npb-mg" runs="2">
				    <args>8 C</args>
					<tuning>
						<procpin>False</procpin>
					</tuning>
				</app>
				<topology nc="8" cpv="4" />
				<mapping idf="4" pstrat="BAL_ONE" />
			</cluster>
		</clusters>
	</experiment>
	<experiment name="nc8-cpv4-idf4-psNONE-ppFalse" trials="1">
		<clusters>
			<cluster>
				<app name="npb-mg" runs="2">
				    <args>8 C</args>
					<tuning>
						<procpin>False</procpin>
					</tuning>
				</app>
				<topology nc="8" cpv="4" />
				<mapping idf="4" pstrat="NONE" />
			</cluster>
		</clusters>
	</experiment>
	<experiment name="nc64-cpv4-idf8-psBAL_ONE-ppFalse" trials="1">
		<clusters>
			<cluster>
				<app name="npb-mg" runs="2">
				    <args>64 C</args>
					<tuning>
						<procpin>False</procpin>
					</tuning>
				</app>
				<topology nc="64" cpv="4" />
				<mapping idf="8" pstrat="BAL_ONE" />
			</cluster>
		</clusters>
	</experiment>
	<experiment name="nc64-cpv4-idf8-psNONE-ppFalse" trials="1">
		<clusters>
			<cluster>
				<app name="npb-mg" runs="2">
				    <args>64 C</args>
					<tuning>
						<procpin>False</procpin>
					</tuning>
				</app>
				<topology nc="64" cpv="4" />
				<mapping idf="8" pstrat="NONE" />
			</cluster>
		</clusters>
	</experiment>
	<experiment name="nc32-cpv4-idf8-psBAL_ONE-ppFalse" trials="1">
		<clusters>
			<cluster>
				<app name="npb-mg" runs="2">
				    <args>32 C</args>
					<tuning>
						<procpin>False</procpin>
					</tuning>
				</app>
				<topology nc="32" cpv="4" />
				<mapping idf="8" pstrat="BAL_ONE" />
			</cluster>
		</clusters>
	</experiment>
	<experiment name="nc32-cpv4-idf8-psNONE-ppFalse" trials="1">
		<clusters>
			<cluster>
				<app name="npb-mg" runs="2">
				    <args>32 C</args>
					<tuning>
						<procpin>False</procpin>
					</tuning>
				</app>
				<topology nc="32" cpv="4" />
				<mapping idf="8" pstrat="NONE" />
			</cluster>
		</clusters>
	</experiment>
	<experiment name="nc16-cpv4-idf8-psBAL_ONE-ppFalse" trials="1">
		<clusters>
			<cluster>
				<app name="npb-mg" runs="2">
				    <args>16 C</args>
					<tuning>
						<procpin>False</procpin>
					</tuning>
				</app>
				<topology nc="16" cpv="4" />
				<mapping idf="8" pstrat="BAL_ONE" />
			</cluster>
		</clusters>
	</experiment>
	<experiment name="nc16-cpv4-idf8-psNONE-ppFalse" trials="1">
		<clusters>
			<cluster>
				<app name="npb-mg" runs="2">
				    <args>16 C</args>
					<tuning>
						<procpin>False</procpin>
					</tuning>
				</app>
				<topology nc="16" cpv="4" />
				<mapping idf="8" pstrat="NONE" />
			</cluster>
		</clusters>
	</experiment>
	<experiment name="nc8-cpv4-idf8-psBAL_ONE-ppFalse" trials="1">
		<clusters>
			<cluster>
				<app name="npb-mg" runs="2">
				    <args>8 C</args>
					<tuning>
						<procpin>False</procpin>
					</tuning>
				</app>
				<topology nc="8" cpv="4" />
				<mapping idf="8" pstrat="BAL_ONE" />
			</cluster>
		</clusters>
	</experiment>
	<experiment name="nc8-cpv4-idf8-psNONE-ppFalse" trials="1">
		<clusters>
			<cluster>
				<app name="npb-mg" runs="2">
				    <args>8 C</args>
					<tuning>
						<procpin>False</procpin>
					</tuning>
				</app>
				<topology nc="8" cpv="4" />
				<mapping idf="8" pstrat="NONE" />
			</cluster>
		</clusters>
	</experiment>
	<experiment name="nc64-cpv8-idf8-psBAL_ONE-ppFalse" trials="1">
		<clusters>
			<cluster>
				<app name="npb-mg" runs="2">
				    <args>64 C</args>
					<tuning>
						<procpin>False</procpin>
					</tuning>
				</app>
				<topology nc="64" cpv="8" />
				<mapping idf="8" pstrat="BAL_ONE" />
			</cluster>
		</clusters>
	</experiment>
	<experiment name="nc64-cpv8-idf8-psNONE-ppFalse" trials="1">
		<clusters>
			<cluster>
				<app name="npb-mg" runs="2">
				    <args>64 C</args>
					<tuning>
						<procpin>False</procpin>
					</tuning>
				</app>
				<topology nc="64" cpv="8" />
				<mapping idf="8" pstrat="NONE" />
			</cluster>
		</clusters>
	</experiment>
	<experiment name="nc32-cpv8-idf8-psBAL_ONE-ppFalse" trials="1">
		<clusters>
			<cluster>
				<app name="npb-mg" runs="2">
				    <args>32 C</args>
					<tuning>
						<procpin>False</procpin>
					</tuning>
				</app>
				<topology nc="32" cpv="8" />
				<mapping idf="8" pstrat="BAL_ONE" />
			</cluster>
		</clusters>
	</experiment>
	<experiment name="nc32-cpv8-idf8-psNONE-ppFalse" trials="1">
		<clusters>
			<cluster>
				<app name="npb-mg" runs="2">
				    <args>32 C</args>
					<tuning>
						<procpin>False</procpin>
					</tuning>
				</app>
				<topology nc="32" cpv="8" />
				<mapping idf="8" pstrat="NONE" />
			</cluster>
		</clusters>
	</experiment>
	<experiment name="nc16-cpv8-idf8-psBAL_ONE-ppFalse" trials="1">
		<clusters>
			<cluster>
				<app name="npb-mg" runs="2">
				    <args>16 C</args>
					<tuning>
						<procpin>False</procpin>
					</tuning>
				</app>
				<topology nc="16" cpv="8" />
				<mapping idf="8" pstrat="BAL_ONE" />
			</cluster>
		</clusters>
	</experiment>
	<experiment name="nc16-cpv8-idf8-psNONE-ppFalse" trials="1">
		<clusters>
			<cluster>
				<app name="npb-mg" runs="2">
				    <args>16 C</args>
					<tuning>
						<procpin>False</procpin>
					</tuning>
				</app>
				<topology nc="16" cpv="8" />
				<mapping idf="8" pstrat="NONE" />
			</cluster>
		</clusters>
	</experiment>
	<experiment name="nc8-cpv8-idf8-psBAL_ONE-ppFalse" trials="1">
		<clusters>
			<cluster>
				<app name="npb-mg" runs="2">
				    <args>8 C</args>
					<tuning>
						<procpin>False</procpin>
					</tuning>
				</app>
				<topology nc="8" cpv="8" />
				<mapping idf="8" pstrat="BAL_ONE" />
			</cluster>
		</clusters>
	</experiment>
	<experiment name="nc8-cpv8-idf8-psNONE-ppFalse" trials="1">
		<clusters>
			<cluster>
				<app name="npb-mg" runs="2">
				    <args>8 C</args>
					<tuning>
						<procpin>False</procpin>
					</tuning>
				</app>
				<topology nc="8" cpv="8" />
				<mapping idf="8" pstrat="NONE" />
			</cluster>
		</clusters>
	</experiment>
</experiments>
